pdfmerge/__init__.py
pdfmerge/__main__.py
pdfmerge/py.typed
pdfmerge-1.0.0.dist-info/LICENSE.md
pdfmerge-1.0.0.dist-info/METADATA
pdfmerge-1.0.0.dist-info/WHEEL
pdfmerge-1.0.0.dist-info/entry_points.txt
pdfmerge-1.0.0.dist-info/top_level.txt
pdfmerge-1.0.0.dist-info/RECORD
