Metadata-Version: 2.1
Name: pdfmerge
Version: 1.0.0
Summary: Command-line utility for merging, splicing, and rotating PDF documents.
Author-email: Metaist LLC <metaist@metaist.com>
License: MIT
Project-URL: Homepage, https://github.com/metaist/pdfmerge
Project-URL: Documentation, https://metaist.github.io/pdfmerge/
Project-URL: Repository, https://github.com/metaist/pdfmerge.git
Project-URL: Changelog, https://github.com/metaist/pdfmerge/blob/main/CHANGELOG.md
Keywords: pdf,merge,split,cli
Classifier: Development Status :: 4 - Beta
Classifier: Environment :: Console
Classifier: Intended Audience :: End Users/Desktop
Classifier: License :: OSI Approved :: MIT License
Classifier: Natural Language :: English
Classifier: Operating System :: OS Independent
Classifier: Programming Language :: Python
Classifier: Programming Language :: Python :: 3
Classifier: Programming Language :: Python :: 3 :: Only
Classifier: Programming Language :: Python :: 3.8
Classifier: Programming Language :: Python :: 3.9
Classifier: Programming Language :: Python :: 3.10
Classifier: Programming Language :: Python :: 3.11
Classifier: Topic :: Utilities
Classifier: Typing :: Typed
Requires-Python: >=3.8
Provides-Extra: dev
License-File: LICENSE.md
